sirena/__init__.py
sirena/base.py
sirena/bin/__init__.py
sirena/bin/cli.py
sirena/erd/__init__.py
sirena/erd/shapes.py
sirena/flowchart/__init__.py
sirena/flowchart/shapes.py
sirena/luigi/__init__.py
sirena/luigi/dynamic.py
sirena/luigi/sample_dag.py
sirena-0.1.1.post2.dist-info/entry_points.txt
sirena-0.1.1.post2.dist-info/LICENSE
sirena-0.1.1.post2.dist-info/WHEEL
sirena-0.1.1.post2.dist-info/METADATA
sirena-0.1.1.post2.dist-info/RECORD
